personalvibe/_README.md
personalvibe/__init__.py
personalvibe/cli.py
personalvibe/data/__init__.py
personalvibe/data/bugfix_template.yaml
personalvibe/data/master.md
personalvibe/data/milestone_template.yaml
personalvibe/data/sprint_template.yaml
personalvibe/data/tasks/bugfix.yaml
personalvibe/data/tasks/milestone.yaml
personalvibe/data/tasks/naked.yaml
personalvibe/data/tasks/sprint.yaml
personalvibe/data/tasks/streamline.yaml
personalvibe/llm_router.py
personalvibe/logger.py
personalvibe/parse_stage.py
personalvibe/py.typed
personalvibe/retry_engine.py
personalvibe/run_context.py
personalvibe/run_pipeline.py
personalvibe/task_config.py
personalvibe/vibe_utils.py
personalvibe/yaml_utils.py
personalvibe-3.0.0.dist-info/LICENSE
personalvibe-3.0.0.dist-info/METADATA
personalvibe-3.0.0.dist-info/WHEEL
personalvibe-3.0.0.dist-info/entry_points.txt
personalvibe-3.0.0.dist-info/RECORD
