Metadata-Version: 2.3
Name: personalvibe
Version: 3.0.0
Summary: My personal vibecoding.
License: MIT
Keywords: flask,personalvibe,python_packaging
Author: Nick Jenkins
Requires-Python: >=3.9,<3.13
Classifier: Development Status :: 4 - Beta
Classifier: Intended Audience :: Education
Classifier: License :: OSI Approved :: MIT License
Classifier: Programming Language :: Python :: 3
Classifier: Programming Language :: Python :: 3.9
Classifier: Programming Language :: Python :: 3.10
Classifier: Programming Language :: Python :: 3.11
Classifier: Programming Language :: Python :: 3.12
Classifier: Programming Language :: Python :: 3 :: Only
Classifier: Topic :: Utilities
Requires-Dist: jinja2 (>=3.1.6,<4.0.0)
Requires-Dist: litellm (>=1.40)
Requires-Dist: nox-poetry (>=1.2.0,<2.0.0)
Requires-Dist: openai (>=1.77.0,<2.0.0)
Requires-Dist: pathspec (>=0.12.1,<0.13.0)
Requires-Dist: pydantic (>=2.0,<3.0)
Requires-Dist: pydantic-settings (>=2.9.1,<3.0.0)
Requires-Dist: python-dotenv (>=0.21,<0.22)
Requires-Dist: pytz (>=2025.1,<2026.0)
Requires-Dist: pyyaml (>=6.0,<7.0)
Requires-Dist: requests (>=2.29,<3.0)
Requires-Dist: tenacity (>=9.0,<10.0)
Requires-Dist: tiktoken (>=0.9.0,<0.10.0)
Requires-Dist: tqdm (>=4.67,<5.0)
Project-URL: Documentation, https://ndjenkins85.github.io/personalvibe/
Project-URL: Homepage, https://www.ndjenkins.com/
Project-URL: Repository, https://github.com/ndjenkins85/personalvibe/
